pyZlBus/__init__.py
pyZlBus/pyZlBus.py
pyZlBus/test.py
pyZlBus/linux/libPyZlBusApi_py310.so
pyZlBus/linux/libPyZlBusApi_py311.so
pyZlBus/linux/libPyZlBusApi_py312.so
pyZlBus/win/PyZlBusApi_py310.pyd
pyZlBus/win/PyZlBusApi_py311.pyd
pyZlBus/win/PyZlBusApi_py312.pyd
pyZlBus-0.1.20.dist-info/METADATA
pyZlBus-0.1.20.dist-info/WHEEL
pyZlBus-0.1.20.dist-info/top_level.txt
pyZlBus-0.1.20.dist-info/RECORD
