Metadata-Version: 2.1
Name: pyZlBus
Version: 0.1.20
Summary: ZeroLab wireless attitude chip, ZLBUS communication protocol API
Home-page: https://www.zero-lab.tech
Author: Larry.lv
Author-email: larry.lv@zero-lab.tech
Classifier: Programming Language :: Python :: 3.10
Classifier: License :: OSI Approved :: MIT License
Classifier: Operating System :: OS Independent
Requires-Python: >=3.10
Requires-Dist: bleak >=0.21.0 ; sys_platform == "linux"
Requires-Dist: bleak >=0.21.0 ; sys_platform == "win32"
